{
    "dataContainers": [
        {
            "playerPos": {
                "x": 0.0,
                "y": 1.600000023841858,
                "z": 0.0
            },
            "timeStamp": 2.58038592338562
        },
        {
            "playerPos": {
                "x": 0.0,
                "y": 1.600000023841858,
                "z": 0.0
            },
            "timeStamp": 4.356425762176514
        },
        {
            "playerPos": {
                "x": 0.0,
                "y": 1.600000023841858,
                "z": 0.0
            },
            "timeStamp": 4.357233047485352
        },
        {
            "playerPos": {
                "x": 0.0,
                "y": 1.600000023841858,
                "z": 0.0
            },
            "timeStamp": 4.358325004577637
        },
        {
            "playerPos": {
                "x": 0.0,
                "y": 1.600000023841858,
                "z": 0.0
            },
            "timeStamp": 4.423264980316162
        },
        {
            "playerPos": {
                "x": 0.0,
                "y": 1.600000023841858,
                "z": 0.0
            },
            "timeStamp": 4.548582077026367
        },
        {
            "playerPos": {
                "x": 0.0,
                "y": 1.600000023841858,
                "z": 0.0
            },
            "timeStamp": 4.671291828155518
        },
        {
            "playerPos": {
                "x": 0.0,
                "y": 1.600000023841858,
                "z": 0.0
            },
            "timeStamp": 4.7982001304626469
        },
        {
            "playerPos": {
                "x": 0.0,
                "y": 1.600000023841858,
                "z": 0.0
            },
            "timeStamp": 4.923460483551025
        },
        {
            "playerPos": {
                "x": 0.0,
                "y": 1.600000023841858,
                "z": 0.0
            },
            "timeStamp": 5.047297954559326
        },
        {
            "playerPos": {
                "x": 0.0,
                "y": 1.600000023841858,
                "z": 0.0
            },
            "timeStamp": 5.173795223236084
        },
        {
            "playerPos": {
                "x": 0.0,
                "y": 1.600000023841858,
                "z": 0.0
            },
            "timeStamp": 5.297521114349365
        },
        {
            "playerPos": {
                "x": -0.0004353081458248198,
                "y": 1.600000023841858,
                "z": -0.008000355213880539
            },
            "timeStamp": 5.423025131225586
        },
        {
            "playerPos": {
                "x": -0.021954761818051339,
                "y": 1.600000023841858,
                "z": -0.2025911659002304
            },
            "timeStamp": 5.548144817352295
        },
        {
            "playerPos": {
                "x": -0.08778753876686096,
                "y": 1.600000023841858,
                "z": -0.5282443165779114
            },
            "timeStamp": 5.673806190490723
        },
        {
            "playerPos": {
                "x": -0.1779073178768158,
                "y": 1.600000023841858,
                "z": -0.88811856508255
            },
            "timeStamp": 5.7978515625
        },
        {
            "playerPos": {
                "x": -0.27376919984817507,
                "y": 1.600000023841858,
                "z": -1.2478162050247193
            },
            "timeStamp": 5.922428131103516
        },
        {
            "playerPos": {
                "x": -0.36196044087409975,
                "y": 1.6000001430511475,
                "z": -1.5716956853866578
            },
            "timeStamp": 6.04882287979126
        },
        {
            "playerPos": {
                "x": -0.39987459778785708,
                "y": 1.6000001430511475,
                "z": -1.710658311843872
            },
            "timeStamp": 6.173280239105225
        },
        {
            "playerPos": {
                "x": -0.41456636786460879,
                "y": 1.6000001430511475,
                "z": -1.7645063400268555
            },
            "timeStamp": 6.296809673309326
        },
        {
            "playerPos": {
                "x": -0.42041781544685366,
                "y": 1.6000001430511475,
                "z": -1.785953164100647
            },
            "timeStamp": 6.424069881439209
        },
        {
            "playerPos": {
                "x": -0.42263489961624148,
                "y": 1.6000001430511475,
                "z": -1.7940788269042969
            },
            "timeStamp": 6.548327922821045
        },
        {
            "playerPos": {
                "x": -0.42349082231521609,
                "y": 1.6000001430511475,
                "z": -1.7972153425216675
            },
            "timeStamp": 6.671894550323486
        },
        {
            "playerPos": {
                "x": -0.423829048871994,
                "y": 1.6000001430511475,
                "z": -1.7984551191329957
            },
            "timeStamp": 6.797347068786621
        },
        {
            "playerPos": {
                "x": -0.4203883707523346,
                "y": 1.6000001430511475,
                "z": -1.8033664226531983
            },
            "timeStamp": 6.923206806182861
        },
        {
            "playerPos": {
                "x": -0.2848840653896332,
                "y": 1.6000001430511475,
                "z": -1.9359469413757325
            },
            "timeStamp": 7.048418998718262
        },
        {
            "playerPos": {
                "x": -0.020560547709465028,
                "y": 1.6000001430511475,
                "z": -2.1267013549804689
            },
            "timeStamp": 7.173168182373047
        },
        {
            "playerPos": {
                "x": 0.30998772382736208,
                "y": 1.5991814136505128,
                "z": -2.29960298538208
            },
            "timeStamp": 7.2977495193481449
        },
        {
            "playerPos": {
                "x": 0.6632103323936462,
                "y": 1.599180817604065,
                "z": -2.4370222091674806
            },
            "timeStamp": 7.42377233505249
        },
        {
            "playerPos": {
                "x": 1.0213147401809693,
                "y": 1.5991804599761963,
                "z": -2.5343692302703859
            },
            "timeStamp": 7.546463966369629
        },
        {
            "playerPos": {
                "x": 1.3908324241638184,
                "y": 1.5991805791854859,
                "z": -2.6139981746673586
            },
            "timeStamp": 7.67246150970459
        },
        {
            "playerPos": {
                "x": 1.763662338256836,
                "y": 1.599179983139038,
                "z": -2.675868034362793
            },
            "timeStamp": 7.797674655914307
        },
        {
            "playerPos": {
                "x": 1.8550961017608643,
                "y": 1.599179983139038,
                "z": -2.538386344909668
            },
            "timeStamp": 7.923667907714844
        },
        {
            "playerPos": {
                "x": 1.963250994682312,
                "y": 1.5991798639297486,
                "z": -2.245925188064575
            },
            "timeStamp": 8.04769515991211
        },
        {
            "playerPos": {
                "x": 2.0970733165740969,
                "y": 1.599179744720459,
                "z": -1.9024500846862794
            },
            "timeStamp": 8.171882629394532
        },
        {
            "playerPos": {
                "x": 2.2345499992370607,
                "y": 1.5991796255111695,
                "z": -1.5553340911865235
            },
            "timeStamp": 8.296320915222168
        },
        {
            "playerPos": {
                "x": 2.425156593322754,
                "y": 1.5991792678833008,
                "z": -1.224990725517273
            },
            "timeStamp": 8.422757148742676
        },
        {
            "playerPos": {
                "x": 2.733635187149048,
                "y": 1.5991790294647217,
                "z": -1.0113328695297242
            },
            "timeStamp": 8.547125816345215
        },
        {
            "playerPos": {
                "x": 3.0948948860168459,
                "y": 1.599178671836853,
                "z": -0.8799006938934326
            },
            "timeStamp": 8.673775672912598
        },
        {
            "playerPos": {
                "x": 3.450924873352051,
                "y": 1.599178433418274,
                "z": -0.7779354453086853
            },
            "timeStamp": 8.79713249206543
        },
        {
            "playerPos": {
                "x": 3.810542106628418,
                "y": 1.5991781949996949,
                "z": -0.6809295415878296
            },
            "timeStamp": 8.921783447265625
        },
        {
            "playerPos": {
                "x": 4.175994396209717,
                "y": 1.5991781949996949,
                "z": -0.5847322344779968
            },
            "timeStamp": 9.047260284423829
        },
        {
            "playerPos": {
                "x": 4.540145397186279,
                "y": 1.5991780757904053,
                "z": -0.48980048298835757
            },
            "timeStamp": 9.172719955444336
        },
        {
            "playerPos": {
                "x": 4.899914264678955,
                "y": 1.599177598953247,
                "z": -0.3983509838581085
            },
            "timeStamp": 9.296310424804688
        },
        {
            "playerPos": {
                "x": 5.276764392852783,
                "y": 1.5991768836975098,
                "z": -0.3394796848297119
            },
            "timeStamp": 9.422816276550293
        },
        {
            "playerPos": {
                "x": 5.657257556915283,
                "y": 1.5991765260696412,
                "z": -0.33425235748291018
            },
            "timeStamp": 9.547982215881348
        },
        {
            "playerPos": {
                "x": 6.032280921936035,
                "y": 1.599176287651062,
                "z": -0.3714035749435425
            },
            "timeStamp": 9.673154830932618
        },
        {
            "playerPos": {
                "x": 6.404763698577881,
                "y": 1.5991761684417725,
                "z": -0.42867904901504519
            },
            "timeStamp": 9.798707008361817
        },
        {
            "playerPos": {
                "x": 6.768688201904297,
                "y": 1.599176287651062,
                "z": -0.4930192232131958
            },
            "timeStamp": 9.922368049621582
        },
        {
            "playerPos": {
                "x": 7.130809783935547,
                "y": 1.5991761684417725,
                "z": -0.6116675734519959
            },
            "timeStamp": 10.046416282653809
        },
        {
            "playerPos": {
                "x": 7.455186367034912,
                "y": 1.5991761684417725,
                "z": -0.8275196552276611
            },
            "timeStamp": 10.173813819885254
        },
        {
            "playerPos": {
                "x": 7.735504627227783,
                "y": 1.5991761684417725,
                "z": -1.0677595138549805
            },
            "timeStamp": 10.296486854553223
        },
        {
            "playerPos": {
                "x": 8.011034965515137,
                "y": 1.599176049232483,
                "z": -1.327515959739685
            },
            "timeStamp": 10.423205375671387
        },
        {
            "playerPos": {
                "x": 8.281957626342774,
                "y": 1.599176049232483,
                "z": -1.592677354812622
            },
            "timeStamp": 10.549028396606446
        },
        {
            "playerPos": {
                "x": 8.54525375366211,
                "y": 1.5991758108139039,
                "z": -1.8529038429260255
            },
            "timeStamp": 10.672341346740723
        },
        {
            "playerPos": {
                "x": 8.857532501220704,
                "y": 1.5991754531860352,
                "z": -2.065467357635498
            },
            "timeStamp": 10.797163009643555
        },
        {
            "playerPos": {
                "x": 9.226052284240723,
                "y": 1.5991753339767457,
                "z": -2.0969865322113039
            },
            "timeStamp": 10.92418384552002
        },
        {
            "playerPos": {
                "x": 9.563161849975586,
                "y": 1.5991750955581666,
                "z": -1.9554661512374879
            },
            "timeStamp": 11.04749870300293
        },
        {
            "playerPos": {
                "x": 9.849077224731446,
                "y": 1.599175214767456,
                "z": -1.7030079364776612
            },
            "timeStamp": 11.17231273651123
        },
        {
            "playerPos": {
                "x": 10.078031539916993,
                "y": 1.5991750955581666,
                "z": -1.3983845710754395
            },
            "timeStamp": 11.297220230102539
        },
        {
            "playerPos": {
                "x": 10.252961158752442,
                "y": 1.599174976348877,
                "z": -1.0592809915542603
            },
            "timeStamp": 11.423338890075684
        },
        {
            "playerPos": {
                "x": 10.37850570678711,
                "y": 1.599174976348877,
                "z": -0.7006276845932007
            },
            "timeStamp": 11.54858112335205
        },
        {
            "playerPos": {
                "x": 10.46640682220459,
                "y": 1.5991748571395875,
                "z": -0.3400457203388214
            },
            "timeStamp": 11.671921730041504
        },
        {
            "playerPos": {
                "x": 10.537837028503418,
                "y": 1.5999789237976075,
                "z": 0.03463200479745865
            },
            "timeStamp": 11.798993110656739
        },
        {
            "playerPos": {
                "x": 10.595620155334473,
                "y": 1.5999782085418702,
                "z": 0.40444475412368777
            },
            "timeStamp": 11.924176216125489
        },
        {
            "playerPos": {
                "x": 10.641816139221192,
                "y": 1.5999776124954224,
                "z": 0.7713247537612915
            },
            "timeStamp": 12.047860145568848
        },
        {
            "playerPos": {
                "x": 10.66719913482666,
                "y": 1.5999772548675538,
                "z": 0.9843434691429138
            },
            "timeStamp": 12.17334270477295
        },
        {
            "playerPos": {
                "x": 10.676953315734864,
                "y": 1.5999771356582642,
                "z": 1.0661957263946534
            },
            "timeStamp": 12.297853469848633
        },
        {
            "playerPos": {
                "x": 10.713025093078614,
                "y": 1.5999770164489747,
                "z": 1.0818253755569459
            },
            "timeStamp": 12.422786712646485
        },
        {
            "playerPos": {
                "x": 10.925432205200196,
                "y": 1.5999770164489747,
                "z": 0.9783116579055786
            },
            "timeStamp": 12.54656982421875
        },
        {
            "playerPos": {
                "x": 11.240862846374512,
                "y": 1.5999767780303956,
                "z": 0.9331896305084229
            },
            "timeStamp": 12.671509742736817
        },
        {
            "playerPos": {
                "x": 11.512801170349121,
                "y": 1.5999765396118165,
                "z": 1.1129964590072632
            },
            "timeStamp": 12.79773235321045
        },
        {
            "playerPos": {
                "x": 11.630180358886719,
                "y": 1.5999760627746583,
                "z": 1.375673770904541
            },
            "timeStamp": 12.92369270324707
        },
        {
            "playerPos": {
                "x": 11.611900329589844,
                "y": 1.5999760627746583,
                "z": 1.377489686012268
            },
            "timeStamp": 13.04894733428955
        },
        {
            "playerPos": {
                "x": 11.485079765319825,
                "y": 1.5999760627746583,
                "z": 1.4138727188110352
            },
            "timeStamp": 13.171388626098633
        },
        {
            "playerPos": {
                "x": 11.251740455627442,
                "y": 1.5946276187896729,
                "z": 1.5348825454711915
            },
            "timeStamp": 13.298177719116211
        },
        {
            "playerPos": {
                "x": 10.933473587036133,
                "y": 1.5336859226226807,
                "z": 1.6981555223464966
            },
            "timeStamp": 13.424309730529786
        },
        {
            "playerPos": {
                "x": 10.624988555908204,
                "y": 1.5336860418319703,
                "z": 1.9115957021713257
            },
            "timeStamp": 13.546443939208985
        },
        {
            "playerPos": {
                "x": 10.352747917175293,
                "y": 1.5336856842041016,
                "z": 2.1794493198394777
            },
            "timeStamp": 13.672404289245606
        },
        {
            "playerPos": {
                "x": 10.13062858581543,
                "y": 1.533685564994812,
                "z": 2.4987285137176515
            },
            "timeStamp": 13.798761367797852
        },
        {
            "playerPos": {
                "x": 10.028131484985352,
                "y": 1.531294584274292,
                "z": 2.865825653076172
            },
            "timeStamp": 13.923515319824219
        },
        {
            "playerPos": {
                "x": 10.12601089477539,
                "y": 1.531294345855713,
                "z": 3.2148287296295168
            },
            "timeStamp": 14.048822402954102
        },
        {
            "playerPos": {
                "x": 10.190855026245118,
                "y": 1.5312941074371338,
                "z": 3.3014135360717775
            },
            "timeStamp": 14.17175006866455
        },
        {
            "playerPos": {
                "x": 10.190855026245118,
                "y": 1.5312941074371338,
                "z": 3.3014135360717775
            },
            "timeStamp": 14.29725456237793
        },
        {
            "playerPos": {
                "x": 10.190855026245118,
                "y": 1.5312941074371338,
                "z": 3.3014135360717775
            },
            "timeStamp": 14.422144889831543
        },
        {
            "playerPos": {
                "x": 10.190855026245118,
                "y": 1.5312941074371338,
                "z": 3.3014135360717775
            },
            "timeStamp": 14.547819137573243
        },
        {
            "playerPos": {
                "x": 10.190855026245118,
                "y": 1.5312941074371338,
                "z": 3.3014135360717775
            },
            "timeStamp": 14.672703742980957
        },
        {
            "playerPos": {
                "x": 10.190855026245118,
                "y": 1.5312941074371338,
                "z": 3.3014135360717775
            },
            "timeStamp": 14.798842430114746
        },
        {
            "playerPos": {
                "x": 10.190855026245118,
                "y": 1.5312941074371338,
                "z": 3.3014135360717775
            },
            "timeStamp": 14.922152519226075
        },
        {
            "playerPos": {
                "x": 10.190855026245118,
                "y": 1.5312941074371338,
                "z": 3.3014135360717775
            },
            "timeStamp": 15.046703338623047
        },
        {
            "playerPos": {
                "x": 10.190855026245118,
                "y": 1.5312941074371338,
                "z": 3.3014135360717775
            },
            "timeStamp": 15.172633171081543
        },
        {
            "playerPos": {
                "x": 10.190855026245118,
                "y": 1.5312941074371338,
                "z": 3.3014135360717775
            },
            "timeStamp": 15.298763275146485
        },
        {
            "playerPos": {
                "x": 10.190855026245118,
                "y": 1.5312941074371338,
                "z": 3.3014135360717775
            },
            "timeStamp": 15.421972274780274
        },
        {
            "playerPos": {
                "x": 10.190855026245118,
                "y": 1.5312941074371338,
                "z": 3.3014135360717775
            },
            "timeStamp": 15.546971321105957
        },
        {
            "playerPos": {
                "x": 10.190855026245118,
                "y": 1.5312941074371338,
                "z": 3.3014135360717775
            },
            "timeStamp": 15.671807289123536
        },
        {
            "playerPos": {
                "x": 10.190855026245118,
                "y": 1.5312941074371338,
                "z": 3.3014135360717775
            },
            "timeStamp": 15.796369552612305
        },
        {
            "playerPos": {
                "x": 10.190855026245118,
                "y": 1.5312941074371338,
                "z": 3.3014135360717775
            },
            "timeStamp": 15.922934532165528
        },
        {
            "playerPos": {
                "x": 10.190855026245118,
                "y": 1.5312941074371338,
                "z": 3.3014135360717775
            },
            "timeStamp": 16.048688888549806
        },
        {
            "playerPos": {
                "x": 10.190855026245118,
                "y": 1.5312941074371338,
                "z": 3.3014135360717775
            },
            "timeStamp": 16.174291610717775
        },
        {
            "playerPos": {
                "x": 10.190855026245118,
                "y": 1.5312941074371338,
                "z": 3.3014135360717775
            },
            "timeStamp": 16.298297882080079
        },
        {
            "playerPos": {
                "x": 10.190855026245118,
                "y": 1.5312941074371338,
                "z": 3.3014135360717775
            },
            "timeStamp": 16.42324447631836
        },
        {
            "playerPos": {
                "x": 10.190855026245118,
                "y": 1.5312941074371338,
                "z": 3.3014135360717775
            },
            "timeStamp": 16.547922134399415
        },
        {
            "playerPos": {
                "x": 10.190855026245118,
                "y": 1.5312941074371338,
                "z": 3.3014135360717775
            },
            "timeStamp": 16.67232894897461
        },
        {
            "playerPos": {
                "x": 10.190855026245118,
                "y": 1.5312941074371338,
                "z": 3.3014135360717775
            },
            "timeStamp": 16.797197341918947
        },
        {
            "playerPos": {
                "x": 10.190855026245118,
                "y": 1.5312941074371338,
                "z": 3.3014135360717775
            },
            "timeStamp": 16.924026489257814
        },
        {
            "playerPos": {
                "x": 10.190855026245118,
                "y": 1.5312941074371338,
                "z": 3.3014135360717775
            },
            "timeStamp": 17.047107696533204
        },
        {
            "playerPos": {
                "x": 10.190855026245118,
                "y": 1.5312941074371338,
                "z": 3.3014135360717775
            },
            "timeStamp": 17.17357635498047
        },
        {
            "playerPos": {
                "x": 10.190855026245118,
                "y": 1.5312941074371338,
                "z": 3.3014135360717775
            },
            "timeStamp": 17.298343658447267
        },
        {
            "playerPos": {
                "x": 10.190855026245118,
                "y": 1.5312941074371338,
                "z": 3.3014135360717775
            },
            "timeStamp": 17.422367095947267
        },
        {
            "playerPos": {
                "x": 10.190855026245118,
                "y": 1.5312941074371338,
                "z": 3.3014135360717775
            },
            "timeStamp": 17.5496768951416
        },
        {
            "playerPos": {
                "x": 10.190855026245118,
                "y": 1.5312941074371338,
                "z": 3.3014135360717775
            },
            "timeStamp": 17.671998977661134
        },
        {
            "playerPos": {
                "x": 10.190855026245118,
                "y": 1.5312941074371338,
                "z": 3.3014135360717775
            },
            "timeStamp": 17.79678726196289
        },
        {
            "playerPos": {
                "x": 10.190855026245118,
                "y": 1.5312941074371338,
                "z": 3.3014135360717775
            },
            "timeStamp": 17.923662185668947
        },
        {
            "playerPos": {
                "x": 10.190855026245118,
                "y": 1.5312941074371338,
                "z": 3.3014135360717775
            },
            "timeStamp": 18.048492431640626
        },
        {
            "playerPos": {
                "x": 10.190855026245118,
                "y": 1.5312941074371338,
                "z": 3.3014135360717775
            },
            "timeStamp": 18.17359733581543
        },
        {
            "playerPos": {
                "x": 10.190855026245118,
                "y": 1.5312941074371338,
                "z": 3.3014135360717775
            },
            "timeStamp": 18.297653198242189
        },
        {
            "playerPos": {
                "x": 10.190855026245118,
                "y": 1.5312941074371338,
                "z": 3.3014135360717775
            },
            "timeStamp": 18.423995971679689
        }
    ]
}